LICENSE
MANIFEST.in
setup.cfg
setup.py
tlsenum/__init__.py
tlsenum/hello_constructs.py
tlsenum/mappings.py
tlsenum/parse_hello.py
tlsenum/utils.py
tlsenum.egg-info/PKG-INFO
tlsenum.egg-info/SOURCES.txt
tlsenum.egg-info/dependency_links.txt
tlsenum.egg-info/entry_points.txt
tlsenum.egg-info/pbr.json
tlsenum.egg-info/requires.txt
tlsenum.egg-info/top_level.txt