Metadata-Version: 1.1
Name: tlsenum
Version: 0.3
Summary: A TLS ciphersuite enumeration tool.
Home-page: https://github.com/Ayrx/tlsenum
Author: Terry Chia
Author-email: terrycwk1994@gmail.com
License: MIT
Platform: UNKNOWN
Classifier: Intended Audience :: Developers
Classifier: Natural Language :: English
Classifier: License :: OSI Approved :: MIT License
Classifier: Operating System :: OS Independent
Classifier: Programming Language :: Python
Classifier: Programming Language :: Python :: 2
Classifier: Programming Language :: Python :: 2.7
Classifier: Programming Language :: Python :: 3
Classifier: Programming Language :: Python :: 3.3
Classifier: Programming Language :: Python :: 3.4
Classifier: Topic :: Security
Classifier: Topic :: Security :: Cryptography
